codec_bpe/__init__.py
codec_bpe/audio_to_codes.py
codec_bpe/extend_tokenizer.py
codec_bpe/lm_dataset_stats.py
codec_bpe/prep_lm_dataset.py
codec_bpe/train_tokenizer.py
codec_bpe/core/__init__.py
codec_bpe/core/converter.py
codec_bpe/core/sentencepiece_bpe.py
codec_bpe/core/trainer.py
codec_bpe/core/utils.py
codec_bpe/tools/__init__.py
codec_bpe/tools/audio_encoder.py
codec_bpe/tools/codec_utils.py
codec_bpe/tools/extender.py
codec_bpe/tools/lm_dataset_builder.py
codec_bpe-1.4.1.dist-info/licenses/LICENSE
codec_bpe-1.4.1.dist-info/METADATA
codec_bpe-1.4.1.dist-info/WHEEL
codec_bpe-1.4.1.dist-info/top_level.txt
codec_bpe-1.4.1.dist-info/RECORD
