Metadata-Version: 2.4
Name: codec-bpe
Version: 1.4.1
Summary: Implementation of Acoustic BPE (Shen et al., 2024), extended for RVQ-based Neural Audio Codecs
Home-page: https://github.com/AbrahamSanders/codec-bpe
Author: Abraham Sanders
Author-email: abraham.sanders@gmail.com
License-File: LICENSE
Requires-Dist: librosa
Requires-Dist: numpy
Requires-Dist: tokenizers>=0.19.0
Requires-Dist: torch
Requires-Dist: transformers>=4.45.0
Provides-Extra: funcodec
Requires-Dist: huggingface-hub; extra == "funcodec"
Requires-Dist: funcodec; extra == "funcodec"
Provides-Extra: xcodec2
Requires-Dist: huggingface-hub; extra == "xcodec2"
Requires-Dist: xcodec2; extra == "xcodec2"
Provides-Extra: wavtokenizer
Requires-Dist: huggingface-hub; extra == "wavtokenizer"
Provides-Extra: simvq
Requires-Dist: huggingface-hub; extra == "simvq"
Requires-Dist: omegaconf; extra == "simvq"
Provides-Extra: magicodec
Requires-Dist: huggingface-hub; extra == "magicodec"
Provides-Extra: neucodec
Requires-Dist: neucodec; extra == "neucodec"
Dynamic: author
Dynamic: author-email
Dynamic: description
Dynamic: description-content-type
Dynamic: home-page
Dynamic: license-file
Dynamic: provides-extra
Dynamic: requires-dist
Dynamic: summary
